graphsagedgl/__init__.py
graphsagedgl/model.py
tests/__init__.py
tests/test_model.py
graphsagedgl-0.1.0.dist-info/LICENSE
graphsagedgl-0.1.0.dist-info/METADATA
graphsagedgl-0.1.0.dist-info/WHEEL
graphsagedgl-0.1.0.dist-info/top_level.txt
graphsagedgl-0.1.0.dist-info/RECORD
