Metadata-Version: 2.1
Name: graphsagedgl
Version: 0.1.0
Summary: GraphSage Implementation using Deep Graph Library.
Home-page: https://github.com/joacoib/graphsagedgl
Author: Joaquin Ignacio Barotto
Author-email: joaquin.barotto@gmail.com
License: UNKNOWN
Platform: UNKNOWN
Classifier: Programming Language :: Python :: 3
Classifier: Development Status :: 2 - Pre-Alpha
Classifier: Intended Audience :: Developers
Classifier: License :: OSI Approved :: GNU General Public License v3 (GPLv3)
License-File: LICENSE
